beetsplug/__init__.py
beetsplug/beetstream/__init__.py
beetsplug/beetstream/albums.py
beetsplug/beetstream/artists.py
beetsplug/beetstream/coverart.py
beetsplug/beetstream/dummy.py
beetsplug/beetstream/playlistprovider.py
beetsplug/beetstream/playlists.py
beetsplug/beetstream/search.py
beetsplug/beetstream/songs.py
beetsplug/beetstream/stream.py
beetsplug/beetstream/users.py
beetsplug/beetstream/utils.py
Beetstream-1.4.0.dist-info/LICENSE
Beetstream-1.4.0.dist-info/METADATA
Beetstream-1.4.0.dist-info/WHEEL
Beetstream-1.4.0.dist-info/top_level.txt
Beetstream-1.4.0.dist-info/RECORD
