Metadata-Version: 2.1
Name: Beetstream
Version: 1.4.0
Summary: Beets.io plugin that expose SubSonic API endpoints, allowing you to stream your music everywhere.
Home-page: https://github.com/BinaryBrain/Beetstream
Author: Binary Brain
Author-email: me@sachabron.ch
Project-URL: Bug Tracker, https://github.com/BinaryBrain/Beetstream/issues
Classifier: Environment :: No Input/Output (Daemon)
Classifier: Intended Audience :: End Users/Desktop
Classifier: Programming Language :: Python :: 3
Classifier: Programming Language :: Python :: 3.8
Classifier: Programming Language :: Python :: 3.9
Classifier: Operating System :: OS Independent
Classifier: Topic :: Multimedia :: Sound/Audio :: Players
Classifier: License :: OSI Approved :: MIT License
Classifier: Framework :: Flask
Requires-Python: >=3.8
License-File: LICENSE
Requires-Dist: flask >=1.1.2
Requires-Dist: flask-cors >=3.0.10
Requires-Dist: Pillow >=8.4.0
Requires-Dist: ffmpeg-python >=0.2.0
